davis_rig_parser/__init__.py
davis_rig_parser/davis_rig_parser.py
davis_rig_parser-0.4.0.dist-info/METADATA
davis_rig_parser-0.4.0.dist-info/WHEEL
davis_rig_parser-0.4.0.dist-info/top_level.txt
davis_rig_parser-0.4.0.dist-info/RECORD
